netcat_py/__init__.py
netcat_py/__main__.py
netcat_py/py.typed
netcat_py-0.0.2.dist-info/WHEEL
netcat_py-0.0.2.dist-info/entry_points.txt
netcat_py-0.0.2.dist-info/METADATA
netcat_py-0.0.2.dist-info/RECORD
