Metadata-Version: 2.3
Name: netcat-py
Version: 0.0.2
Summary: NetCat in Python
Author: Zeev Rotshtein
Author-email: Zeev Rotshtein <zeevro@gmail.com>
Requires-Python: >=3.10
Project-URL: Repository, https://github.com/zeevro/netcat-py
